milvus_geo_bench/__init__.py
milvus_geo_bench/benchmark.py
milvus_geo_bench/cli.py
milvus_geo_bench/dataset.py
milvus_geo_bench/evaluator.py
milvus_geo_bench/grid_manager.py
milvus_geo_bench/milvus_client.py
milvus_geo_bench/utils.py
milvus_geo_bench-0.1.0.dist-info/METADATA
milvus_geo_bench-0.1.0.dist-info/WHEEL
milvus_geo_bench-0.1.0.dist-info/entry_points.txt
milvus_geo_bench-0.1.0.dist-info/RECORD
