Metadata-Version: 2.4
Name: milvus-geo-bench
Version: 0.1.0
Summary: Benchmark tool for Milvus geo search functionality
Author-email: zhuwenxing <wenxing.zhu@zilliz.com>
Requires-Python: >=3.12
Requires-Dist: click>=8.0.0
Requires-Dist: numpy>=1.24.0
Requires-Dist: pandas>=2.0.0
Requires-Dist: pyarrow>=14.0.0
Requires-Dist: pymilvus==2.7.0rc29
Requires-Dist: pyproj>=3.4.0
Requires-Dist: python-dotenv>=1.0.0
Requires-Dist: pyyaml>=6.0
Requires-Dist: shapely>=2.0.0
Requires-Dist: tabulate>=0.9.0
Requires-Dist: tqdm>=4.65.0
Provides-Extra: dev
Requires-Dist: ruff>=0.6.0; extra == 'dev'
